efax/__init__.py
efax/py.typed
efax/_src/__init__.py
efax/_src/expectation_parametrization.py
efax/_src/iteration.py
efax/_src/natural_parametrization.py
efax/_src/parametrization.py
efax/_src/tools.py
efax/_src/types.py
efax/_src/distributions/__init__.py
efax/_src/distributions/bernoulli.py
efax/_src/distributions/beta.py
efax/_src/distributions/chi.py
efax/_src/distributions/chi_square.py
efax/_src/distributions/dirichlet.py
efax/_src/distributions/dirichlet_common.py
efax/_src/distributions/exponential.py
efax/_src/distributions/gamma.py
efax/_src/distributions/gen_dirichlet.py
efax/_src/distributions/geometric.py
efax/_src/distributions/inverse_gamma.py
efax/_src/distributions/inverse_gaussian.py
efax/_src/distributions/logarithmic.py
efax/_src/distributions/multinomial.py
efax/_src/distributions/negative_binomial.py
efax/_src/distributions/negative_binomial_common.py
efax/_src/distributions/poisson.py
efax/_src/distributions/rayleigh.py
efax/_src/distributions/von_mises.py
efax/_src/distributions/weibull.py
efax/_src/distributions/cmvn/__init__.py
efax/_src/distributions/cmvn/circularly_symmetric.py
efax/_src/distributions/cmvn/unit_variance.py
efax/_src/distributions/complex_normal/__init__.py
efax/_src/distributions/complex_normal/complex_normal.py
efax/_src/distributions/complex_normal/unit_variance.py
efax/_src/distributions/log_normal/__init__.py
efax/_src/distributions/log_normal/log_normal.py
efax/_src/distributions/log_normal/unit_variance.py
efax/_src/distributions/multivariate_normal/__init__.py
efax/_src/distributions/multivariate_normal/arbitrary.py
efax/_src/distributions/multivariate_normal/diagonal.py
efax/_src/distributions/multivariate_normal/fixed_variance.py
efax/_src/distributions/multivariate_normal/isotropic.py
efax/_src/distributions/multivariate_normal/unit_variance.py
efax/_src/distributions/normal/__init__.py
efax/_src/distributions/normal/normal.py
efax/_src/distributions/normal/unit_variance.py
efax-1.23.0.dist-info/METADATA
efax-1.23.0.dist-info/WHEEL
efax-1.23.0.dist-info/licenses/LICENSE
efax-1.23.0.dist-info/RECORD
