Metadata-Version: 2.4
Name: efax
Version: 1.23.0
Summary: Exponential families for JAX
Project-URL: source, https://github.com/NeilGirdhar/efax
Author: Neil Girdhar
Author-email: mistersheik@gmail.com
Maintainer: Neil Girdhar
Maintainer-email: mistersheik@gmail.com
License-Expression: Apache-2.0
License-File: LICENSE
Classifier: Development Status :: 5 - Production/Stable
Classifier: Intended Audience :: Science/Research
Classifier: License :: OSI Approved :: Apache Software License
Classifier: Operating System :: OS Independent
Classifier: Programming Language :: Python
Classifier: Programming Language :: Python :: 3
Classifier: Programming Language :: Python :: 3.12
Classifier: Programming Language :: Python :: 3.13
Classifier: Programming Language :: Python :: 3.14
Classifier: Topic :: Scientific/Engineering :: Artificial Intelligence
Classifier: Topic :: Software Development :: Libraries :: Python Modules
Classifier: Typing :: Typed
Requires-Python: <3.15,>=3.12
Requires-Dist: array-api-compat>=1.10
Requires-Dist: array-api-extra>=0.8
Requires-Dist: jax>=0.6.1
Requires-Dist: numpy>=1.25
Requires-Dist: opt-einsum>=3.4
Requires-Dist: optimistix>=0.0.9
Requires-Dist: optype[numpy]>=0.8.0
Requires-Dist: scipy-stubs>=1.15
Requires-Dist: scipy>=1.15
Requires-Dist: tfp-nightly>=0.25
Requires-Dist: tjax>=1.4.1
Requires-Dist: typing-extensions>=4.8
